legion_cli/__init__.py
legion_cli/alerts_manager.py
legion_cli/cli.py
legion_cli/config.py
legion_cli/log.py
legion_cli/tui/__init__.py
legion_cli/tui/alerts_monitor.py
legion_cli/tui/detail_list.py
legion_cli/tui/keyboard.py
legion_cli-0.4.1.dist-info/entry_points.txt
legion_cli-0.4.1.dist-info/WHEEL
legion_cli-0.4.1.dist-info/METADATA
legion_cli-0.4.1.dist-info/licenses/LICENSE
legion_cli-0.4.1.dist-info/RECORD
