Metadata-Version: 2.1
Name: legion-cli
Version: 0.4.1
Summary: Commandline Utilities for the Legion Alerting and Monitoring System
License: GPL-3.0-or-later
Author-email: Eugene Kovalev <eugene@kovalev.systems>
Requires-Python: <4.0,>3.9.0
Requires-Dist: click>=8.0
Requires-Dist: legion-utils>=0.3.3
Requires-Dist: rich>=10.8.0
Requires-Dist: termcolor>=1.1
